<Properties StartupConfiguration="{799334D5-B136-475A-8FCF-117987019744}|https" GitUserInfo="UsingMD">
  <MultiItemStartupConfigurations />
  <MonoDevelop.Ide.DebuggingService.Breakpoints>
    <BreakpointStore />
  </MonoDevelop.Ide.DebuggingService.Breakpoints>
  <MonoDevelop.Ide.Workspace ActiveConfiguration="Debug" />
  <MonoDevelop.Ide.DebuggingService.PinnedWatches />
  <MonoDevelop.Ide.Workbench ActiveDocument="src/MyApp.API/Controllers/UserController.cs">
    <Files>
      <File FileName="src/MyApp.API/Program.cs" />
      <File FileName="src/MyApp.API/appsettings.json" />
      <File FileName="src/MyApp.Application/Interfaces/IOtpService.cs" />
      <File FileName="src/MyApp.Application/Services/User/OtpService.cs" />
      <File FileName="src/MyApp.Application/Services/User/UserService.cs" />
      <File FileName="src/MyApp.API/Controllers/UserController.cs" Line="170" Column="1" />
      <File FileName="src/MyApp.Domain/Entities/ApplicationUser.cs" />
      <File FileName="src/MyApp.Application/DTOs/OtpDtos.cs" />
      <File FileName="src/MyApp.Application/Services/User/AuthService.cs" />
      <File FileName="src/MyApp.Application/DTOs/ApiResponse.cs" />
      <File FileName="src/MyApp.Infrastructure/Repositories/GenericRepository.cs" />
      <File FileName="src/MyApp.Application/Interfaces/IGenericRepository.cs" />
      <File FileName="src/MyApp.Infrastructure/Repositories/OtpCodesRepository.cs" />
      <File FileName="src/MyApp.Application/Interfaces/IOtpCodesRepository.cs" />
    </Files>
    <Pads>
      <Pad Id="ProjectPad">
        <State name="__root__">
          <Node name="MyApp" expanded="True">
            <Node name="src" expanded="True">
              <Node name="MyApp.API" expanded="True">
                <Node name="Controllers" expanded="True" />
              </Node>
            </Node>
          </Node>
        </State>
      </Pad>
    </Pads>
  </MonoDevelop.Ide.Workbench>
  <MonoDevelop.Ide.ItemProperties.src.MyApp.API PreferredExecutionTarget="/System/Volumes/Preboot/Cryptexes/App/System/Applications/Safari.app" />
</Properties>